{"errors":[],"warnings":[],"namedChunkGroups":{"app":{"chunks":[6,0,2],"assets":["webpack-runtime-68154e5247618a9b50fd.js","webpack-runtime-68154e5247618a9b50fd.js.map","commons-e94e2be8a22657c7914e.js","commons-e94e2be8a22657c7914e.js.map","app-0cfae85e837fdccb9e1a.js","app-0cfae85e837fdccb9e1a.js.map"],"children":{},"childAssets":{}},"component---src-pages-404-js":{"chunks":[1,0,3],"assets":["styles.15b7c0f8c10598316e58.css","styles-6a63fa93f4a2e10daa13.js","styles-6a63fa93f4a2e10daa13.js.map","commons-e94e2be8a22657c7914e.js","commons-e94e2be8a22657c7914e.js.map","component---src-pages-404-js-937d1b115ca56d3e6694.js","component---src-pages-404-js-937d1b115ca56d3e6694.js.map"],"children":{},"childAssets":{}},"component---src-pages-index-js":{"chunks":[1,0,4],"assets":["styles.15b7c0f8c10598316e58.css","styles-6a63fa93f4a2e10daa13.js","styles-6a63fa93f4a2e10daa13.js.map","commons-e94e2be8a22657c7914e.js","commons-e94e2be8a22657c7914e.js.map","component---src-pages-index-js-685c5bd4fba705fce6bc.js","component---src-pages-index-js-685c5bd4fba705fce6bc.js.map"],"children":{},"childAssets":{}},"component---src-pages-page-2-js":{"chunks":[1,0,5],"assets":["styles.15b7c0f8c10598316e58.css","styles-6a63fa93f4a2e10daa13.js","styles-6a63fa93f4a2e10daa13.js.map","commons-e94e2be8a22657c7914e.js","commons-e94e2be8a22657c7914e.js.map","component---src-pages-page-2-js-9091273db8b77923343d.js","component---src-pages-page-2-js-9091273db8b77923343d.js.map"],"children":{},"childAssets":{}}},"assetsByChunkName":{"app":["webpack-runtime-68154e5247618a9b50fd.js","commons-e94e2be8a22657c7914e.js","app-0cfae85e837fdccb9e1a.js"],"component---src-pages-404-js":["styles.15b7c0f8c10598316e58.css","styles-6a63fa93f4a2e10daa13.js","commons-e94e2be8a22657c7914e.js","component---src-pages-404-js-937d1b115ca56d3e6694.js"],"component---src-pages-index-js":["styles.15b7c0f8c10598316e58.css","styles-6a63fa93f4a2e10daa13.js","commons-e94e2be8a22657c7914e.js","component---src-pages-index-js-685c5bd4fba705fce6bc.js"],"component---src-pages-page-2-js":["styles.15b7c0f8c10598316e58.css","styles-6a63fa93f4a2e10daa13.js","commons-e94e2be8a22657c7914e.js","component---src-pages-page-2-js-9091273db8b77923343d.js"]}}